prepush/__init__.py
prepush/__main__.py
prepush-1.1.0.dist-info/LICENSE
prepush-1.1.0.dist-info/METADATA
prepush-1.1.0.dist-info/WHEEL
prepush-1.1.0.dist-info/entry_points.txt
prepush-1.1.0.dist-info/top_level.txt
prepush-1.1.0.dist-info/RECORD
