Metadata-Version: 2.1
Name: prepush
Version: 1.1.0
Summary: check, which ci workflows will be triggered after your push
Author-email: Dhanush Arivappagari <4rivappa@proton.me>
License: Copyright © 2024 4rivappa
Project-URL: Homepage, https://github.com/4rivappa/prepush
Keywords: ci,github actions,workflows
Classifier: License :: OSI Approved :: MIT License
Classifier: Programming Language :: Python
Classifier: Programming Language :: Python :: 3
Requires-Python: >=3.6
License-File: LICENSE
Requires-Dist: pyyaml
